main.py
mssql.py
mcp_mssql_server-0.1.0.dist-info/licenses/LICENSE
mcp_mssql_server-0.1.0.dist-info/METADATA
mcp_mssql_server-0.1.0.dist-info/WHEEL
mcp_mssql_server-0.1.0.dist-info/entry_points.txt
mcp_mssql_server-0.1.0.dist-info/top_level.txt
mcp_mssql_server-0.1.0.dist-info/RECORD
