Metadata-Version: 2.4
Name: mcp-mssql-server
Version: 0.1.0
Summary: A Model Context Protocol server for Microsoft SQL Server with data analysis and visualization capabilities
Author-email: Serena XiaoNaHang Sinclair <serena_hang@hotmail.com>
License-Expression: MIT
Project-URL: Homepage, https://github.com/SerenaHangSinclair/mcp-mssql-server
Project-URL: Repository, https://github.com/SerenaHangSinclair/mcp-mssql-server
Keywords: mcp,mssql,sql-server,database,claude
Classifier: Development Status :: 4 - Beta
Classifier: Intended Audience :: Developers
Classifier: Programming Language :: Python :: 3
Classifier: Programming Language :: Python :: 3.10
Classifier: Programming Language :: Python :: 3.11
Classifier: Programming Language :: Python :: 3.12
Requires-Python: >=3.10
License-File: LICENSE
Requires-Dist: httpx>=0.28.1
Requires-Dist: fastmcp>=0.1.0
Requires-Dist: pymssql>=2.2.8
Requires-Dist: python-dotenv>=1.0.0
Requires-Dist: pandas>=2.0.0
Requires-Dist: matplotlib>=3.7.0
Requires-Dist: seaborn>=0.12.0
Requires-Dist: plotly>=5.14.0
Requires-Dist: nbformat>=5.9.0
Requires-Dist: ipykernel>=6.25.0
Requires-Dist: neo4j>=5.14.0
Requires-Dist: networkx>=3.1.0
Dynamic: license-file
